README.txt
setup.py
hashcalclib/__init__.py
hashcalclib/commonutil.py
hashcalclib/hashcalclib.py
hashcalclib.egg-info/PKG-INFO
hashcalclib.egg-info/SOURCES.txt
hashcalclib.egg-info/dependency_links.txt
hashcalclib.egg-info/not-zip-safe
hashcalclib.egg-info/top_level.txt